[
    {
        "title": "Чистый код. Создание, анализ и рефракторинг",
        "link": "https://www.googleapis.com/books/v1/volumes/2zjECwAAQBAJ",
        "read": true
    },
    {
        "title": "Идеальный программист. Как стать профессионалом разработки ПО",
        "link": "https://www.googleapis.com/books/v1/volumes/Ab7DCwAAQBAJ",
        "read": true
    },
    {
        "title": "Чистая архитектура. Искусство разработки программного обеспечения",
        "link": "https://www.googleapis.com/books/v1/volumes/d6JSDwAAQBAJ",
        "read": true
    },
    {
        "title": "Чистый Agile. Основы гибкости",
        "link": "https://www.googleapis.com/books/v1/volumes/0ZnsDwAAQBAJ",
        "read": true
    },
    {
        "title": "Архитектура корпоративных программных приложений",
        "link": "https://www.googleapis.com/books/v1/volumes/MdMM1ZrICnsC",
        "read": true
    },
    {
        "title": "Приемы объектно-ориентированного проектирования",
        "link": "https://www.googleapis.com/books/v1/volumes/PQayAAAACAAJ",
        "read": true
    },
    {
        "title": "С++",
        "link": "https://www.googleapis.com/books/v1/volumes/ixxYPzpL3mYC",
        "read": true
    },
    {
        "title": "Qt 5.10. Профессиональное программирование на C++",
        "link": "https://www.googleapis.com/books/v1/volumes/J4N0DwAAQBAJ",
        "read": true
    },
    {
        "title": "Паттерны Kubernetes: Шаблоны разработки собственных облачных приложений",
        "link": "https://www.googleapis.com/books/v1/volumes/2pTcDwAAQBAJ",
        "read": false
    },
    {
        "title": "MongoDB",
        "link": "https://www.googleapis.com/books/v1/volumes/8SwQzgEACAAJ",
        "read": false
    },
    {
        "title": "Современные операционные системы. 4-е изд.",
        "link": "https://www.googleapis.com/books/v1/volumes/zA7ECwAAQBAJ",
        "read": true
    },
    {
        "title": "Building Microservices",
        "link": "https://www.googleapis.com/books/v1/volumes/1uUDoQEACAAJ",
        "read": true
    },
    {
        "title": "Data Structures & Algorithms in Java",
        "link": "https://www.googleapis.com/books/v1/volumes/yIudQgAACAAJ",
        "read": true
    },
    {
        "title": "Structured Computer Organization",
        "link": "https://www.googleapis.com/books/v1/volumes/m0HHygAACAAJ",
        "read": false
    },
    {
        "title": "The Design of Web APIs",
        "link": "https://www.googleapis.com/books/v1/volumes/L7MtvgEACAAJ",
        "read": true
    },
    {
        "title": "Компьютерные сети",
        "link": "https://www.googleapis.com/books/v1/volumes/yeQyAAAACAAJ",
        "read": true
    },
    {
        "title": "Не заставляйте меня думать. Веб-юзабилити и здравый смысл",
        "link": "https://www.googleapis.com/books/v1/volumes/NH4oDwAAQBAJ",
        "read": false
    }
]